[
    {
        "i": 34,
        "j": "_GJldn1wQvw",
        "b": "JAVA: Precedencia de operadores ☕ DAM - DAW",
        "h": "20221018103049",
        "l": 1065
    },
    {
        "i": 200,
        "j": "-j4ZuT6YYMo",
        "b": "JAVA Swing: Clase Graphics ☕ DAM - DAW",
        "h": "20230809134804",
        "l": 1125
    },
    {
        "i": 191,
        "j": "-vJE6jLgMGY",
        "b": "Introducción a JAVA Swing: JFrame ☕ DAM - DAW",
        "h": "20230701162334",
        "l": 894
    },
    {
        "i": 92,
        "j": "-w_PxsBWjgU",
        "b": "✅ DAM - DAW: Examen JAVA Resuelto - PRÁCTICO ☕ 1a Evaluación",
        "h": "20230115120650",
        "l": 2062
    },
    {
        "i": 75,
        "j": "03CCpdROuMo",
        "b": "JAVA: Ejercicio String con bordes ☕ DAM - DAW",
        "h": "20221202133210",
        "l": 1878
    },
    {
        "i": 44,
        "j": "06SuspX0TG0",
        "b": "JAVA: Bucle FOR ☕ DAM - DAW",
        "h": "20221025071140",
        "l": 1278
    },
    {
        "i": 144,
        "j": "0pKO9cNG0ns",
        "b": "JAVA: Ejercicio Iteradores ☕ DAM - DAW",
        "h": "20230517212151",
        "l": 1109
    },
    {
        "i": 173,
        "j": "0tN_yrTwLPY",
        "b": "JAVA: Ejemplos clase File ☕ DAM - DAW",
        "h": "20230507154111",
        "l": 987
    },
    {
        "i": 132,
        "j": "1I5Wxy6ZFbw",
        "b": "JAVA: try - catch - finally ☕ DAM - DAW",
        "h": "20230226210014",
        "l": 1315
    },
    {
        "i": 96,
        "j": "1Ivd5SL-mwg",
        "b": "Características de la programación orientada a objetos ☕ DAM - DAW",
        "h": "20230119153717",
        "l": 762
    },
    {
        "i": 148,
        "j": "1kXIFVYVp48",
        "b": "Colecciones en JAVA - Collection & Map ☕ DAM - DAW",
        "h": "20230321204441",
        "l": 950
    },
    {
        "i": 125,
        "j": "1Uh9RNSkaLM",
        "b": "JAVA: La clase Object ☕ DAM - DAW",
        "h": "20230217153306",
        "l": 714
    },
    {
        "i": 64,
        "j": "2_BAUlOufLQ",
        "b": "JAVA: Ejercicios resueltos recursividad ☕ DAM - DAW",
        "h": "20221115182733",
        "l": 2764
    },
    {
        "i": 48,
        "j": "2EJ45xrbR7Y",
        "b": "JAVA: Llaves, Scope e indentado ☕ DAM - DAW",
        "h": "20221028104100",
        "l": 902
    },
    {
        "i": 172,
        "j": "2GjrBo2SRP8",
        "b": "JAVA: La clase File ☕ DAM - DAW",
        "h": "20230504185524",
        "l": 1201
    },
    {
        "i": 76,
        "j": "3b20yV6geXc",
        "b": "JAVA: Ejercicio Arrays con Bordes ☕ DAM - DAW",
        "h": "20221203165151",
        "l": 1091
    },
    {
        "i": 12,
        "j": "3FIomL6wFFM",
        "b": "Ejercicios resueltos pseudocódigo  ☕ DAM - DAW",
        "h": "20220926122200",
        "l": 1155
    },
    {
        "i": 149,
        "j": "3K1_lj2CABU",
        "b": "JAVA: Interface List ☕ DAM - DAW",
        "h": "20230322205727",
        "l": 675
    },
    {
        "i": 212,
        "j": "3pRevR7Pml4",
        "b": "JAVA FX: Clase Node ☕ DAM - DAW",
        "h": "20230910202606",
        "l": 1472
    },
    {
        "i": 74,
        "j": "3VFKuMH5Qg0",
        "b": "JAVA: Ejercicio matriz irregular máxima ☕ DAM - DAW",
        "h": "20221130210900",
        "l": 1428
    },
    {
        "i": 25,
        "j": "443VORsWj2M",
        "b": "JAVA: Clase String ☕ DAM - DAW",
        "h": "20221011112951",
        "l": 1449
    },
    {
        "i": 79,
        "j": "4Dnxv_dtfQ0",
        "b": "JAVA: El famoso String[ ] args ☕ DAM - DAW",
        "h": "20221209122402",
        "l": 691
    },
    {
        "i": 190,
        "j": "4m8tpgLhdVE",
        "b": "JAVA: Ejercicios BDs y ficheros ☕ DAM - DAW",
        "h": "20230627155735",
        "l": 649
    },
    {
        "i": 60,
        "j": "4mjBa6oQN14",
        "b": "JAVA: Ejercicio pila de llamadas ☕ DAM - DAW",
        "h": "20221110203757",
        "l": 827
    },
    {
        "i": 29,
        "j": "4NIgC5ArKTI",
        "b": "JAVA: Operadores matemáticos ☕ DAM - DAW",
        "h": "20221014104110",
        "l": 966
    },
    {
        "i": 141,
        "j": "4Wqiackpdgk",
        "b": "JAVA: Estructuras de datos ☕ DAM - DAW",
        "h": "20230309214648",
        "l": 1713
    },
    {
        "i": 185,
        "j": "4XWBdh1PWo0",
        "b": "MySQL en JAVA: UPDATE ☕ DAM - DAW",
        "h": "20230612203054",
        "l": 894
    },
    {
        "i": 35,
        "j": "4znSjME7tNU",
        "b": "JAVA: Clase Math ☕ DAM - DAW",
        "h": "20221019090318",
        "l": 430
    },
    {
        "i": 146,
        "j": "5ch7D89vpL0",
        "b": "JAVA: Interface Comparator ☕ DAM - DAW",
        "h": "20230317162731",
        "l": 670
    },
    {
        "i": 112,
        "j": "5CX4PiQUP5k",
        "b": "JAVA: Clase inmutable con Array de objetos ☕ DAM - DAW",
        "h": "20230204174607",
        "l": 850
    },
    {
        "i": 28,
        "j": "5EaHrvmoLEk",
        "b": "JAVA: Recomendaciones al declarar variables ☕ DAM - DAW",
        "h": "20221013213832",
        "l": 544
    },
    {
        "i": 183,
        "j": "5eMr5hX--Wk",
        "b": "MySQL en JAVA: SELECT ☕ DAM - DAW",
        "h": "20230608210241",
        "l": 907
    },
    {
        "i": 150,
        "j": "5MPgf5aGAFo",
        "b": "JAVA: LinkedList ☕ DAM - DAW",
        "h": "20230323180754",
        "l": 914
    },
    {
        "i": 87,
        "j": "5nWAU7WwhoM",
        "b": "JAVA: Ejercicios matrices ☕ DAM - DAW",
        "h": "20230109200901",
        "l": 821
    },
    {
        "i": 165,
        "j": "6Fq7dUFiUYM",
        "b": "JAVA: Method reference ☕ DAM - DAW",
        "h": "20230426203107",
        "l": 916
    },
    {
        "i": 108,
        "j": "72i5vVL3Sc0",
        "b": "JAVA: Clases inmutables ☕ DAM - DAW",
        "h": "20230131180736",
        "l": 1067
    },
    {
        "i": 207,
        "j": "7FD6uajkNPQ",
        "b": "JAVA Swing: Juego mecanografía ☕ DAM - DAW",
        "h": "20230830193629",
        "l": 1899
    },
    {
        "i": 110,
        "j": "7IPH-Tbtb74",
        "b": "JAVA: ArrayList ☕ DAM - DAW",
        "h": "20230202190918",
        "l": 1142
    },
    {
        "i": 83,
        "j": "7qvFbFzmqBk",
        "b": "JAVA: Ordenar Arrays - burbuja ☕ DAM - DAW",
        "h": "20221214212614",
        "l": 752
    },
    {
        "i": 16,
        "j": "8gkaitxt-CI",
        "b": "Introducción a JAVA ☕ DAM - DAW",
        "h": "20221002094733",
        "l": 868
    },
    {
        "i": 52,
        "j": "8jNcf21kvbk",
        "b": "JAVA: Ejercicios resueltos FIGURAS ☕ DAM - DAW",
        "h": "20221101213207",
        "l": 1180
    },
    {
        "i": 80,
        "j": "8nBfF4pQKLY",
        "b": "JAVA: Varargs ☕ DAM - DAW",
        "h": "20221211204950",
        "l": 519
    },
    {
        "i": 216,
        "j": "8Rv4SHZ-9xM",
        "b": "JAVA FX: Uso de CSS ☕ DAM - DAW",
        "h": "20230918190741",
        "l": 2297
    },
    {
        "i": 152,
        "j": "8Vq04jsVaRo",
        "b": "JAVA: HashSet + equals + hashCode ☕ DAM - DAW",
        "h": "20230326203447",
        "l": 1025
    },
    {
        "i": 140,
        "j": "8vur2nVczn0",
        "b": "JAVA: Ejercicios finales OO ☕ DAM - DAW",
        "h": "20230523203523",
        "l": 2345
    },
    {
        "i": 4,
        "j": "98m39gc3YpM",
        "b": "Introducción a la programación: operadores relaciones ☕ DAM - DAW",
        "h": "20220920133708",
        "l": 468
    },
    {
        "i": 65,
        "j": "9CQZ1HpXroc",
        "b": "JAVA: Arrays ☕ DAM - DAW",
        "h": "20221116170125",
        "l": 701
    },
    {
        "i": 21,
        "j": "9OpBxj5kYss",
        "b": "JAVA: Declarar variables numéricas ☕ DAM - DAW",
        "h": "20221007113012",
        "l": 1097
    },
    {
        "i": 22,
        "j": "9P8M1V0XnVo",
        "b": "JAVA: El sistema hexadecimal ☕ DAM - DAW",
        "h": "20221009152000",
        "l": 1520
    },
    {
        "i": 182,
        "j": "9xybdEJmLWc",
        "b": "Bases de datos en JAVA: MySQL ☕ DAM - DAW",
        "h": "20230607162807",
        "l": 1818
    },
    {
        "i": 175,
        "j": "ajcnc2O4f_A",
        "b": "JAVA: PrintWriter y Scanner ☕ DAM - DAW",
        "h": "20230509211548",
        "l": 1516
    },
    {
        "i": 129,
        "j": "AkjbCun5kA8",
        "b": "JAVA: Tipos enumerados ☕ DAM - DAW",
        "h": "20230222203715",
        "l": 1042
    },
    {
        "i": 41,
        "j": "AV5hyYaJIw8",
        "b": "JAVA: switch (con int, char y String) ☕ DAM - DAW",
        "h": "20221023083201",
        "l": 814
    },
    {
        "i": 18,
        "j": "AVEU8AEZ5YE",
        "b": "Hola Mundo en JAVA  ☕ DAM - DAW",
        "h": "20221004122926",
        "l": 736
    },
    {
        "i": 73,
        "j": "aX1-dcCMP7A",
        "b": "JAVA: Ejercicio matriz máxima ☕ DAM - DAW",
        "h": "20221128212448",
        "l": 862
    },
    {
        "i": 82,
        "j": "AXcdQEt_LEs",
        "b": "JAVA: Copiar y clonar Arrays ☕ DAM - DAW",
        "h": "20221213213955",
        "l": 640
    },
    {
        "i": 2,
        "j": "b003s0CJ2KU",
        "b": "Representación de algoritmos  ☕ DAM - DAW",
        "h": "20220919142059",
        "l": 593
    },
    {
        "i": 49,
        "j": "b6RWMp7vOe8",
        "b": "JAVA: Casting y Parse ☕ DAM - DAW",
        "h": "20221029120353",
        "l": 629
    },
    {
        "i": 203,
        "j": "Bcdf6KlVNto",
        "b": "JAVA Swing: JFileChooser y JColorChooser ☕ DAM - DAW",
        "h": "20230821200629",
        "l": 1059
    },
    {
        "i": 10,
        "j": "bRwz1J9hxEg",
        "b": "Bucle REPETIR MIENTRAS pseudocódigo (DO-WHILE)  ☕ DAM - DAW",
        "h": "20220925155036",
        "l": 417
    },
    {
        "i": 101,
        "j": "bU0p5XVOM_4",
        "b": "JAVA: Ejemplo clase Televisor ☕ DAM - DAW",
        "h": "20230124170853",
        "l": 489
    },
    {
        "i": 195,
        "j": "Bu2sCL8gaHs",
        "b": "JAVA Swing: Eventos en componentes ☕ DAM - DAW",
        "h": "20230712161156",
        "l": 796
    },
    {
        "i": 107,
        "j": "BugfoJ-ZM6U",
        "b": "JAVA: Paso por referencia y por valor ☕ DAM - DAW",
        "h": "20230130202116",
        "l": 755
    },
    {
        "i": 124,
        "j": "c53SKnJe7Dw",
        "b": "JAVA: Polimorfismo ☕ DAM - DAW",
        "h": "20230216151159",
        "l": 699
    },
    {
        "i": 138,
        "j": "C5O5_tW6jYw",
        "b": "JAVA: Ejercicio Final Excepciones ☕ DAM - DAW",
        "h": "20230307183331",
        "l": 2567
    },
    {
        "i": 202,
        "j": "cCDmOduFgEY",
        "b": "JAVA Swing: Ventanas emergentes ☕ DAM - DAW",
        "h": "20230820103812",
        "l": 1493
    },
    {
        "i": 193,
        "j": "cGy3fYsS3ns",
        "b": "JAVA Swing: Componentes ☕ DAM - DAW",
        "h": "20230707204446",
        "l": 673
    },
    {
        "i": 86,
        "j": "CPXwJ0Top90",
        "b": "JAVA: Generadores de matrices ☕ DAM - DAW",
        "h": "20221229154453",
        "l": 1148
    },
    {
        "i": 204,
        "j": "cQj8oaLMiaE",
        "b": "JAVA Swing: Mini - Paint ☕ DAM - DAW",
        "h": "20230822195847",
        "l": 2567
    },
    {
        "i": 169,
        "j": "cTGPgMMKxZk",
        "b": "JAVA: Programación funcional avanzada ☕ DAM - DAW",
        "h": "20230501204453",
        "l": 1143
    },
    {
        "i": 163,
        "j": "CzLI7DzzQhM",
        "b": "JAVA: Clases y paquetes ☕ DAM - DAW",
        "h": "20230424203411",
        "l": 1509
    },
    {
        "i": 130,
        "j": "D3DBfrWnBJo",
        "b": "JAVA: equals y hashCode ☕ DAM - DAW",
        "h": "20230223194152",
        "l": 1439
    },
    {
        "i": 51,
        "j": "D5rLwK2a0H4",
        "b": "JAVA: Ejercicios resueltos STRINGS ☕ DAM - DAW",
        "h": "20221031101923",
        "l": 1258
    },
    {
        "i": 1,
        "j": "dfEEG4A_Hoo",
        "b": "Introducción a la programación y los algoritmos  ☕ DAM - DAW",
        "h": "20220919142059",
        "l": 1218
    },
    {
        "i": 30,
        "j": "DIbhR5cdtL0",
        "b": "JAVA: Asignaciones complejas ☕ DAM - DAW",
        "h": "20221015072338",
        "l": 935
    },
    {
        "i": 217,
        "j": "djm_Cd67nuE",
        "b": "JAVA FX: Proyecto Final ☕ DAM - DAW",
        "h": "20230921183425",
        "l": 2772
    },
    {
        "i": 54,
        "j": "dmZUegjUUDQ",
        "b": "JAVA: Declaración de métodos ☕ DAM - DAW",
        "h": "20221104134751",
        "l": 1306
    },
    {
        "i": 118,
        "j": "dNh6j0zs6J8",
        "b": "JAVA: Ejercicios OO JAVA - Cuentas bancarias ☕ DAM - DAW",
        "h": "20230210171834",
        "l": 2141
    },
    {
        "i": 147,
        "j": "dRvRFNWk1sw",
        "b": "JAVA: Interface Comparator múltiple ☕ DAM - DAW",
        "h": "20230320190118",
        "l": 870
    },
    {
        "i": 215,
        "j": "dUbNtI4bQZo",
        "b": "JAVA FX: Eventos ☕ DAM - DAW",
        "h": "20230915195628",
        "l": 2621
    },
    {
        "i": 20,
        "j": "dy1qD-jwcIs",
        "b": "JAVA: Tipos de variables ☕ DAM - DAW",
        "h": "20221006104207",
        "l": 945
    },
    {
        "i": 199,
        "j": "e5DdHf45GzQ",
        "b": "JAVA Swing: Eventos mouse ☕ DAM - DAW",
        "h": "20230805151239",
        "l": 741
    },
    {
        "i": 24,
        "j": "EAEVn9JKP9Q",
        "b": "Strings en JAVA  ☕ DAM - DAW",
        "h": "20221011111444",
        "l": 1012
    },
    {
        "i": 78,
        "j": "EAu8ZQDIa-8",
        "b": "JAVA: Ejercicio Matriz doble ☕ DAM - DAW",
        "h": "20221208175354",
        "l": 1092
    },
    {
        "i": 121,
        "j": "ElXzrqK2BSc",
        "b": "JAVA: Introducción a la Herencia ☕ DAM - DAW",
        "h": "20230213193509",
        "l": 996
    },
    {
        "i": 156,
        "j": "eplBXJarh1A",
        "b": "JAVA: HashMap  ☕ DAM - DAW",
        "h": "20230402201443",
        "l": 1203
    },
    {
        "i": 123,
        "j": "EqiUftNakIs",
        "b": "JAVA: Sobrescritura de métodos ☕ DAM - DAW",
        "h": "20230215210100",
        "l": 1022
    },
    {
        "i": 214,
        "j": "ESLDAQ-CC4M",
        "b": "JAVA FX: Bindings y propiedades ☕ DAM - DAW",
        "h": "20230912200042",
        "l": 2290
    },
    {
        "i": 63,
        "j": "EWj58e5NxjI",
        "b": "JAVA: Triángulo recursivo en JAVA ☕ DAM - DAW",
        "h": "20221114174452",
        "l": 1496
    },
    {
        "i": 209,
        "j": "fDZ-wT3b2Nw",
        "b": "Introducción a Maven ☕ DAM - DAW",
        "h": "20230905200320",
        "l": 1690
    },
    {
        "i": 100,
        "j": "FL3qVam0T78",
        "b": "JAVA: Ejemplo clase Círculo ☕ DAM - DAW",
        "h": "20230123153953",
        "l": 740
    },
    {
        "i": 126,
        "j": "FL7yrY9bU3Q",
        "b": "JAVA: Clases abstractas ☕ DAM - DAW",
        "h": "20230219205004",
        "l": 706
    },
    {
        "i": 26,
        "j": "FNjyxclZmDQ",
        "b": "JAVA: Ejercicio String y funciones ☕ DAM - DAW",
        "h": "20221013111700",
        "l": 496
    },
    {
        "i": 197,
        "j": "fxJgVGVFwZk",
        "b": "JAVA Swing: Eventos teclado ☕ DAM - DAW",
        "h": "20230726152704",
        "l": 499
    },
    {
        "i": 46,
        "j": "G1myD-SF3d8",
        "b": "JAVA: Break y continue ☕ DAM - DAW",
        "h": "20221026171438",
        "l": 568
    },
    {
        "i": 42,
        "j": "gE6LpyYgdQY",
        "b": "JAVA: El operador ternario ☕ DAM - DAW",
        "h": "20221024125339",
        "l": 979
    },
    {
        "i": 104,
        "j": "gE9D6Yc0cuA",
        "b": "JAVA: Ejemplo Clase Punto OO ☕ DAM - DAW",
        "h": "20230127192917",
        "l": 1051
    },
    {
        "i": 119,
        "j": "gVVrpTPwSdE",
        "b": "JAVA: OO + UML - Agenda ☕ DAM - DAW",
        "h": "20230211185133",
        "l": 819
    },
    {
        "i": 5,
        "j": "GwwRkMo012Y",
        "b": "Introducción a la programación: operadores lógicos ☕ DAM - DAW",
        "h": "20220921132828",
        "l": 1097
    },
    {
        "i": 8,
        "j": "gWYWRs9d_ZI",
        "b": "Tipos de bucles pseudocódigo (MIENTRAS - WHILE)  ☕ DAM - DAW ]👈",
        "h": "20220923111756",
        "l": 932
    },
    {
        "i": 158,
        "j": "H3_Wuis_Ipg",
        "b": "JAVA: TreeMap anidado ☕ DAM - DAW",
        "h": "20230410135138",
        "l": 1303
    },
    {
        "i": 62,
        "j": "hFOkonKc1V4",
        "b": "JAVA: Recursividad ☕ DAM - DAW",
        "h": "20221113194628",
        "l": 841
    },
    {
        "i": 210,
        "j": "HOr5djeytsA",
        "b": "Introducción a JAVA FX ☕ DAM - DAW",
        "h": "20230907152848",
        "l": 2194
    },
    {
        "i": 194,
        "j": "Hskkm0BtV4c",
        "b": "JAVA Swing y AWT: Eventos ☕ DAM - DAW",
        "h": "20230709202502",
        "l": 1100
    },
    {
        "i": 38,
        "j": "HSq3rRfBmDg",
        "b": "JAVA: Entrada de datos - Clase Scanner  ☕ DAM - DAW",
        "h": "20221020220916",
        "l": 628
    },
    {
        "i": 105,
        "j": "HxvLFdLys8g",
        "b": "JAVA: this ☕ DAM - DAW",
        "h": "20230128170000",
        "l": 922
    },
    {
        "i": 57,
        "j": "I17uuWAMe88",
        "b": "JAVA: Variables locales y globales ☕ DAM - DAW",
        "h": "20221107200604",
        "l": 620
    },
    {
        "i": 106,
        "j": "iaTOo8k7icg",
        "b": "JAVA: static - métodos y variables ☕ DAM - DAW",
        "h": "20230129181059",
        "l": 1195
    },
    {
        "i": 61,
        "j": "IEFj_dDz31g",
        "b": "JAVA: Menú de opciones con métodos ☕ DAM - DAW",
        "h": "20221111160710",
        "l": 762
    },
    {
        "i": 11,
        "j": "ijz6rAu5Trw",
        "b": "Bucle PARA pseudocódigo (FOR)  ☕ DAM - DAW",
        "h": "20220925164840",
        "l": 527
    },
    {
        "i": 174,
        "j": "iuRM-VRgOEM",
        "b": "JAVA: FileReader y FileWriter ☕ DAM - DAW",
        "h": "20230508204859",
        "l": 892
    },
    {
        "i": 50,
        "j": "IVIAZN561LU",
        "b": "JAVA: Ejercicios de iniciación resueltos ☕ DAM - DAW",
        "h": "20221030163939",
        "l": 1621
    },
    {
        "i": 68,
        "j": "iWLzt6g6b5o",
        "b": "JAVA: Matrices ☕ DAM - DAW",
        "h": "20221121203220",
        "l": 893
    },
    {
        "i": 66,
        "j": "iXrWbslAPxs",
        "b": "JAVA: Declarar Arrays ☕ DAM - DAW",
        "h": "20221117162304",
        "l": 783
    },
    {
        "i": 36,
        "j": "jKs6kq6z1sI",
        "b": "JAVA: Funciones matemáticas ☕ DAM - DAW",
        "h": "20221019175010",
        "l": 1141
    },
    {
        "i": 177,
        "j": "JUQcm0pxbHc",
        "b": "JAVA: Ejercicios resueltos ficheros ☕ DAM - DAW",
        "h": "20230516203200",
        "l": 1793
    },
    {
        "i": 77,
        "j": "JvqSCs2ZDW8",
        "b": "JAVA: Ejercicio Matrices con bordes ☕ DAM - DAW",
        "h": "20221207150452",
        "l": 3326
    },
    {
        "i": 136,
        "j": "KDxzgJ-HRQY",
        "b": "JAVA: Excepciones - Ejemplo completo ☕ DAM - DAW",
        "h": "20230303163713",
        "l": 1738
    },
    {
        "i": 55,
        "j": "kKryKJUThhQ",
        "b": "JAVA: Ejercicios sencillos métodos ☕ DAM - DAW",
        "h": "20221105165613",
        "l": 708
    },
    {
        "i": 115,
        "j": "kPtYnLHWPtw",
        "b": "JAVA: Ejercicios OO - Triángulos ☕ DAM - DAW",
        "h": "20230207164906",
        "l": 940
    },
    {
        "i": 59,
        "j": "KS0IEW-iceY",
        "b": "JAVA: La pila de llamadas ☕ DAM - DAW",
        "h": "20221109181507",
        "l": 733
    },
    {
        "i": 161,
        "j": "KT59aB-YQM4",
        "b": "API de JAVA - Time ☕ DAM - DAW",
        "h": "20230420162200",
        "l": 1087
    },
    {
        "i": 69,
        "j": "kU1chyIQU7o",
        "b": "JAVA: Recorrer Matrices ☕ DAM - DAW",
        "h": "20221122120546",
        "l": 619
    },
    {
        "i": 109,
        "j": "LAgn2SC9O8E",
        "b": "JAVA: Arrays de objetos ☕ DAM - DAW",
        "h": "20230201204734",
        "l": 518
    },
    {
        "i": 176,
        "j": "LeLR8C8FsUE",
        "b": "JAVA: BufferedWriter y BufferedReader ☕ DAM - DAW",
        "h": "20230511201134",
        "l": 1143
    },
    {
        "i": 168,
        "j": "liBESrRvJNM",
        "b": "JAVA: Ejemplos API Stream ☕ DAM - DAW",
        "h": "20230429203529",
        "l": 1435
    },
    {
        "i": 90,
        "j": "lIoJOxoUA3Y",
        "b": "JAVA: Quicksort vs Mergesort vs Heapsort ☕ DAM - DAW",
        "h": "20230112163640",
        "l": 1062
    },
    {
        "i": 39,
        "j": "lqUz-UQMuiI",
        "b": "JAVA: Condiciones if - else  ☕ DAM - DAW",
        "h": "20221021114513",
        "l": 928
    },
    {
        "i": 206,
        "j": "lt_1BJlPIhM",
        "b": "JAVA Swing: Cronómetro ☕ DAM - DAW",
        "h": "20230825135516",
        "l": 1044
    },
    {
        "i": 70,
        "j": "lVM9KB3iDQo",
        "b": "JAVA: Matrices irregulares ☕ DAM - DAW",
        "h": "20221123204945",
        "l": 853
    },
    {
        "i": 131,
        "j": "lWC9rt0vBek",
        "b": "JAVA: Excepciones ☕ DAM - DAW",
        "h": "20230225181852",
        "l": 1221
    },
    {
        "i": 23,
        "j": "mAi5o9rsJS4",
        "b": "JAVA: Char y boolean + ASCII + UNICODE  ☕ DAM - DAW",
        "h": "20221010113506",
        "l": 1026
    },
    {
        "i": 95,
        "j": "mNt0D-pKmU4",
        "b": "JAVA: Ejemplos orientación a objetos ☕ DAM - DAW",
        "h": "20230118135528",
        "l": 1130
    },
    {
        "i": 137,
        "j": "N_h8K_-roRM",
        "b": "JAVA: Ejercicio Final Herencia ☕ DAM - DAW",
        "h": "20230306141517",
        "l": 2156
    },
    {
        "i": 111,
        "j": "N--60I7OyIs",
        "b": "JAVA: Ejemplos ArrayList ☕ DAM - DAW",
        "h": "20230203180340",
        "l": 963
    },
    {
        "i": 58,
        "j": "n92sGOeWPFY",
        "b": "JAVA: Sobrecarga de métodos ☕ DAM - DAW",
        "h": "20221108170534",
        "l": 763
    },
    {
        "i": 208,
        "j": "NDL2LJkM5vE",
        "b": "JAVA Swing: Quicksort ☕ DAM - DAW",
        "h": "20230831182757",
        "l": 1473
    },
    {
        "i": 0,
        "j": "NFDjCN4r_68",
        "b": "Presentación MEGA Curso JAVA desde 0 ☕️ DAM - DAW",
        "h": "20220919142059",
        "l": 789
    },
    {
        "i": 117,
        "j": "NJs-Jss3ZBs",
        "b": "JAVA: Ejercicios OO + UML - Cuentas bancarias ☕ DAM - DAW",
        "h": "20230209121910",
        "l": 1708
    },
    {
        "i": 31,
        "j": "nJUURIe3Nc0",
        "b": "JAVA: Operadores relacionales ☕ DAM - DAW",
        "h": "20221016171635",
        "l": 847
    },
    {
        "i": 37,
        "j": "noQbTZdYYZo",
        "b": "JAVA: Decimales y precisión ☕ DAM - DAW",
        "h": "20221020111929",
        "l": 604
    },
    {
        "i": 120,
        "j": "OtvGFeLyMmY",
        "b": "JAVA: Soluciones Agenda OO ☕ DAM - DAW",
        "h": "20230212205646",
        "l": 1055
    },
    {
        "i": 178,
        "j": "ov2EoNfxIdA",
        "b": "JAVA: Ficheros binarios ☕ DAM - DAW",
        "h": "20230529201704",
        "l": 1580
    },
    {
        "i": 211,
        "j": "oxqKvOvTn6c",
        "b": "JAVA FX: HolaMundo ☕ DAM - DAW",
        "h": "20230909193540",
        "l": 1572
    },
    {
        "i": 180,
        "j": "p2zgGu4nOCc",
        "b": "JAVA: Serialización ☕ DAM - DAW",
        "h": "20230531205353",
        "l": 907
    },
    {
        "i": 9,
        "j": "P73Sa4dzvoc",
        "b": "Ejercicio bucle mientras en pseudocódigo ☕ DAM - DAW",
        "h": "20220924095151",
        "l": 482
    },
    {
        "i": 27,
        "j": "p7p9f7wKd9Y",
        "b": "JAVA: Secuencias de escape ☕ DAM - DAW",
        "h": "20221013195109",
        "l": 776
    },
    {
        "i": 3,
        "j": "pgF8U9WxPts",
        "b": "Variables y expresiones aritméticas ☕ DAM - DAW",
        "h": "20220920112229",
        "l": 960
    },
    {
        "i": 166,
        "j": "pip5g8KfNUo",
        "b": "JAVA: Programación funcional ☕ DAM - DAW",
        "h": "20230427163222",
        "l": 1146
    },
    {
        "i": 189,
        "j": "POAbMRr9vkw",
        "b": "MySQL en JAVA: Encriptar datos ☕ DAM - DAW",
        "h": "20230623165151",
        "l": 1183
    },
    {
        "i": 155,
        "j": "PQcBEX5M23c",
        "b": "JAVA: Interface Map ☕ DAM - DAW",
        "h": "20230330200119",
        "l": 1511
    },
    {
        "i": 91,
        "j": "pUBBuTAd0Co",
        "b": "✅ DAM - DAW: Examen JAVA Resuelto - TEST ☕ 1a Evaluación",
        "h": "20230113121033",
        "l": 1007
    },
    {
        "i": 56,
        "j": "pWf9Q95NFtY",
        "b": "JAVA: Paso por valor ☕ DAM - DAW",
        "h": "20221106165833",
        "l": 532
    },
    {
        "i": 170,
        "j": "PwnUcPdz9bU",
        "b": "JAVA: Ejercicios Colecciones ☕ DAM - DAW",
        "h": "20230525203858",
        "l": 2145
    },
    {
        "i": 17,
        "j": "Q_2j8aYnmYk",
        "b": "JAVA: Preparando el entorno (JRE, JDK y VS Code)  ☕ DAM - DAW",
        "h": "20221003113521",
        "l": 509
    },
    {
        "i": 160,
        "j": "q3TCmzpaiIk",
        "b": "API de JAVA ☕ DAM - DAW",
        "h": "20230418154620",
        "l": 1167
    },
    {
        "i": 159,
        "j": "Q4s1RMSXzX8",
        "b": "JAVA: TreeMap avanzado ☕ DAM - DAW",
        "h": "20230415064213",
        "l": 1194
    },
    {
        "i": 43,
        "j": "qao5b2S9y0g",
        "b": "JAVA: Bucle WHILE y DO - WHILE ☕ DAM - DAW",
        "h": "20221024193944",
        "l": 914
    },
    {
        "i": 135,
        "j": "QdYBKihDzog",
        "b": "JAVA: Excepciones de usuario ☕ DAM - DAW",
        "h": "20230301205939",
        "l": 914
    },
    {
        "i": 67,
        "j": "QIdiaJcDBHI",
        "b": "JAVA: Ejercicios iniciación Arrays ☕ DAM - DAW",
        "h": "20221118115738",
        "l": 1342
    },
    {
        "i": 19,
        "j": "QRDePHN91UY",
        "b": "JAVA: Salida por pantalla ☕ DAM - DAW",
        "h": "20221005143712",
        "l": 644
    },
    {
        "i": 205,
        "j": "qZbXj9njg5Q",
        "b": "JAVA Swing: Tres en Raya ☕ DAM - DAW",
        "h": "20230825093757",
        "l": 954
    },
    {
        "i": 145,
        "j": "R_gV5wpBwNQ",
        "b": "JAVA: Interface Comparable ☕ DAM - DAW",
        "h": "20230315193205",
        "l": 963
    },
    {
        "i": 162,
        "j": "r_W7qc7hUBw",
        "b": "API de JAVA: Period y Duration ☕ DAM - DAW",
        "h": "20230423170500",
        "l": 1037
    },
    {
        "i": 98,
        "j": "r-H3VYQujgo",
        "b": "JAVA: Mapas de objetos ☕ DAM - DAW",
        "h": "20230121170333",
        "l": 518
    },
    {
        "i": 198,
        "j": "R98K2NnFbXY",
        "b": "JAVA Swing: Imágenes e iconos ☕ DAM - DAW",
        "h": "20230801103125",
        "l": 1464
    },
    {
        "i": 13,
        "j": "rH60985e4PM",
        "b": "Seguimiento de algoritmos  ☕ DAM - DAW",
        "h": "20220927115700",
        "l": 835
    },
    {
        "i": 99,
        "j": "rlNf7toQST8",
        "b": "JAVA: Introducción a la POO ☕ DAM - DAW",
        "h": "20230122203830",
        "l": 1222
    },
    {
        "i": 143,
        "j": "rpFq5O9XIAg",
        "b": "JAVA: Interface Iterable ☕ DAM - DAW",
        "h": "20230313192638",
        "l": 1364
    },
    {
        "i": 192,
        "j": "rYFZNvJwMx4",
        "b": "JAVA Swing: Layout Manager ☕ DAM - DAW",
        "h": "20230703155034",
        "l": 690
    },
    {
        "i": 139,
        "j": "RZG7SQOZn3w",
        "b": "JAVA: Ejercicios resueltos OO ☕ DAM - DAW",
        "h": "20230518194556",
        "l": 1354
    },
    {
        "i": 181,
        "j": "s8Ea7478mmA",
        "b": "JAVA: Ficheros con java.nio ☕ DAM - DAW",
        "h": "20230601202629",
        "l": 1461
    },
    {
        "i": 196,
        "j": "SawioBQDAvA",
        "b": "JAVA Swing: Ejercicios iniciación ☕ DAM - DAW",
        "h": "20230723093332",
        "l": 1526
    },
    {
        "i": 122,
        "j": "SF4GBfn_VmE",
        "b": "JAVA: Ejemplo Herencia - Persona y Estudiante ☕ DAM - DAW",
        "h": "20230214170113",
        "l": 685
    },
    {
        "i": 6,
        "j": "taSJeALBVGk",
        "b": "Instrucciones en pseudocódigo ☕ DAM - DAW",
        "h": "20220922075922",
        "l": 541
    },
    {
        "i": 93,
        "j": "tELkj4CmvgY",
        "b": "Programación orientada a objetos ☕ DAM - DAW",
        "h": "20230116185928",
        "l": 755
    },
    {
        "i": 153,
        "j": "tfeQrUH7L4k",
        "b": "JAVA: TreeSet ☕ DAM - DAW",
        "h": "20230327212414",
        "l": 693
    },
    {
        "i": 94,
        "j": "tfLy9Eu7aNM",
        "b": "JAVA: Elementos básicos de la POO ☕ DAM - DAW",
        "h": "20230117125005",
        "l": 784
    },
    {
        "i": 134,
        "j": "TjhbybnfCcs",
        "b": "JAVA: throws múltiple ☕ DAM - DAW",
        "h": "20230228180004",
        "l": 900
    },
    {
        "i": 7,
        "j": "tldDbZ9MSoA",
        "b": "Estructuras de control alternativas pseudocódigo (SI -  IFS) ☕☕ DAM - DAW",
        "h": "20220922131044",
        "l": 584
    },
    {
        "i": 72,
        "j": "TuoUO2Nd4tA",
        "b": "JAVA: Ejercicio matrices ☕ DAM - DAW",
        "h": "20221127112539",
        "l": 694
    },
    {
        "i": 113,
        "j": "ua7OoQKsdRQ",
        "b": "JAVA: Clase inmutable con ArrayList de objetos ☕ DAM - DAW",
        "h": "20230205211022",
        "l": 756
    },
    {
        "i": 47,
        "j": "UNbB2ItfccQ",
        "b": "JAVA: Bucles FOR anidados ☕ DAM - DAW",
        "h": "20221027105554",
        "l": 1145
    },
    {
        "i": 157,
        "j": "unbN9nF-ifE",
        "b": "JAVA: TreeMap ☕ DAM - DAW",
        "h": "20230404154315",
        "l": 1165
    },
    {
        "i": 154,
        "j": "UPYECuGiePc",
        "b": "JAVA: TreeSet avanzado ☕ DAM - DAW",
        "h": "20230328195116",
        "l": 1308
    },
    {
        "i": 33,
        "j": "uSc0-5I0dzU",
        "b": "JAVA: Operadores bit a bit en ☕ DAM - DAW",
        "h": "20221017180337",
        "l": 819
    },
    {
        "i": 14,
        "j": "V-WDyYJqPnY",
        "b": "Seguimiento de algoritmo con bucles anidados  ☕ DAM - DAW",
        "h": "20220928133535",
        "l": 659
    },
    {
        "i": 89,
        "j": "V1SxDa1jOe4",
        "b": "JAVA: Pruebas matrices ☕ DAM - DAW",
        "h": "20230111095403",
        "l": 1012
    },
    {
        "i": 167,
        "j": "veV_KRiloBY",
        "b": "JAVA: Ejemplos programación funcional ☕ DAM - DAW",
        "h": "20230428181600",
        "l": 1039
    },
    {
        "i": 171,
        "j": "VjU_B45Chbw",
        "b": "JAVA: Ficheros - java.io y java.nio ☕ DAM - DAW",
        "h": "20230502204741",
        "l": 840
    },
    {
        "i": 164,
        "j": "w-mff14ooOg",
        "b": "JAVA: Interfaces funcionales y lambdas ☕ DAM - DAW",
        "h": "20230425201535",
        "l": 968
    },
    {
        "i": 53,
        "j": "wFw1AEDM_TM",
        "b": "Métodos en JAVA ☕ DAM - DAW",
        "h": "20221103210546",
        "l": 643
    },
    {
        "i": 188,
        "j": "wZ1PsCQAlsI",
        "b": "MySQL en JAVA: Binarios ☕ DAM - DAW",
        "h": "20230619160348",
        "l": 1389
    },
    {
        "i": 45,
        "j": "XcxhYxAXCL0",
        "b": "JAVA: Ejemplos bucle FOR ☕ DAM - DAW",
        "h": "20221026072617",
        "l": 638
    },
    {
        "i": 114,
        "j": "Xhe6GA7wa9o",
        "b": "JAVA: Ejercicios OO - Clase Empleado ☕ DAM - DAW",
        "h": "20230206165457",
        "l": 811
    },
    {
        "i": 133,
        "j": "XnQuyV86bOI",
        "b": "JAVA: throw y throws ☕ DAM - DAW",
        "h": "20230227213652",
        "l": 1602
    },
    {
        "i": 97,
        "j": "XTqP4R0MXHw",
        "b": "Diseño orientado a objetos en UML ☕ DAM - DAW",
        "h": "20230120164800",
        "l": 1846
    },
    {
        "i": 84,
        "j": "Xx84_1aWV60",
        "b": "JAVA: Quicksort ☕ DAM - DAW",
        "h": "20221219214136",
        "l": 1299
    },
    {
        "i": 71,
        "j": "Yiywcodl-w0",
        "b": "JAVA: Arrays con foreach ☕ DAM - DAW",
        "h": "20221124203733",
        "l": 631
    },
    {
        "i": 128,
        "j": "yqfOawJPE3M",
        "b": "JAVA: Interfaces ☕ DAM - DAW",
        "h": "20230221193300",
        "l": 592
    },
    {
        "i": 102,
        "j": "ys9QFPbsDiU",
        "b": "JAVA: Sobrecarga de constructores ☕ DAM - DAW",
        "h": "20230125204955",
        "l": 1014
    },
    {
        "i": 85,
        "j": "YswFFA5Tx_8",
        "b": "JAVA: Búsqueda binaria ☕ DAM - DAW",
        "h": "20221220213644",
        "l": 661
    },
    {
        "i": 201,
        "j": "Ywl8WSyTSn4",
        "b": "JAVA Swing: Clase Graphics2D ☕ DAM - DAW",
        "h": "20230813183507",
        "l": 1666
    },
    {
        "i": 151,
        "j": "Yzs5MGu_lJY",
        "b": "JAVA: Set y HashSet ☕ DAM - DAW",
        "h": "20230325172016",
        "l": 1098
    },
    {
        "i": 184,
        "j": "z-DFvBJcJzs",
        "b": "MySQL en JAVA: INSERT ☕ DAM - DAW",
        "h": "20230611153215",
        "l": 842
    },
    {
        "i": 32,
        "j": "Z06XfYcrDN4",
        "b": "JAVA: Operadores lógicos ☕ DAM - DAW",
        "h": "20221017112441",
        "l": 1114
    },
    {
        "i": 186,
        "j": "z2UOpGsHslU",
        "b": "MySQL en JAVA: DELETE ☕ DAM - DAW",
        "h": "20230613171541",
        "l": 848
    },
    {
        "i": 81,
        "j": "ZbcMPoJcJQ8",
        "b": "JAVA: Varargs con matrices ☕ DAM - DAW",
        "h": "20221212224257",
        "l": 1339
    },
    {
        "i": 142,
        "j": "zBE4fx9QyoY",
        "b": "JAVA: Iterable e Iterator ☕ DAM - DAW",
        "h": "20230310184642",
        "l": 1237
    },
    {
        "i": 116,
        "j": "zdw-0PBgU-g",
        "b": "JAVA: Ejercicios OO: Clase Gráfico 2D ☕ DAM - DAW",
        "h": "20230208170100",
        "l": 1587
    },
    {
        "i": 103,
        "j": "zgjT_i_eORA",
        "b": "JAVA: Ejercicios OO Clase Televisor ☕ DAM - DAW",
        "h": "20230126202440",
        "l": 861
    },
    {
        "i": 213,
        "j": "ZqFSvySxVBM",
        "b": "JAVA FX: Layouts ☕ DAM - DAW",
        "h": "20230911171521",
        "l": 857
    },
    {
        "i": 187,
        "j": "ZU53wH-BNfA",
        "b": "MySQL en JAVA: Imágenes ☕ DAM - DAW",
        "h": "20230615202322",
        "l": 1323
    },
    {
        "i": 179,
        "j": "ZusJ9y_bEe8",
        "b": "JAVA: RandomAccessFile ☕ DAM - DAW",
        "h": "20230530201048",
        "l": 727
    },
    {
        "i": 40,
        "j": "ZXXvJ9reA0w",
        "b": "JAVA: Ejemplos if - else ☕ DAM - DAW",
        "h": "20221022160815",
        "l": 537
    },
    {
        "i": 88,
        "j": "ZyGYo3pIylA",
        "b": "JAVA: Matriz transpuesta ☕ DAM - DAW",
        "h": "20230110174715",
        "l": 788
    },
    {
        "i": 127,
        "j": "ZyZ6Tbg9HkM",
        "b": "JAVA: Ejercicios Clase Triángulo ☕ DAM - DAW",
        "h": "20230220151517",
        "l": 1299
    },
    {
        "i": 15,
        "j": "ZzFF_aXLO5g",
        "b": "PSEUDOCÓDIGO: Ejercicios resueltos ☕ DAM - DAW",
        "h": "20220929125123",
        "l": 1190
    }
]