[
    {
        "i": 32,
        "j": "-fxt6Hwf5fM",
        "b": "Curso de Microsoft Power BI desde cero | DAX, FUNCION DISTINCT (video 33)",
        "h": "20231004231352",
        "l": 415
    },
    {
        "i": 39,
        "j": "0Ac_MkFGb58",
        "b": "Curso de Microsoft Power BI desde cero | RELACION DE TABLAS UNO A MUCHOS [EJERCICIO] (video 40)",
        "h": "20240305173521",
        "l": 483
    },
    {
        "i": 37,
        "j": "1nTEowuiXnU",
        "b": "Curso de Microsoft Power BI desde cero | PRACTICA RELACION ENTRE TABLAS (video 38)",
        "h": "20240304180414",
        "l": 1241
    },
    {
        "i": 44,
        "j": "21NfovomS3s",
        "b": "Curso de Microsoft Power BI desde cero | LAYOUTS Y STORYTELLING(video 45)",
        "h": "20240315120646",
        "l": 668
    },
    {
        "i": 67,
        "j": "4CWkbOtj6oo",
        "b": "Curso de Microsoft Power BI desde cero | DINAMIZACION DE COLUMNAS (video 68)",
        "h": "20240404204138",
        "l": 534
    },
    {
        "i": 59,
        "j": "4GssAcKZ0Xs",
        "b": "Curso de Microsoft Power BI desde cero | CARGA DE DATOS DOCUMENTACION (video 60)",
        "h": "20240329155609",
        "l": 354
    },
    {
        "i": 25,
        "j": "4Q8ziZGFBro",
        "b": "Curso de Microsoft Power BI desde cero | TEMAS [INTRODUCCION] (video 26)",
        "h": "20230424223232",
        "l": 533
    },
    {
        "i": 3,
        "j": "4xEsi_YSxtE",
        "b": "Curso de Microsoft Power BI desde cero | IMPORTAR DATOS DESDE ARCHIVO CSV (video 4)",
        "h": "20230408205837",
        "l": 313
    },
    {
        "i": 33,
        "j": "5IchK_h8lsk",
        "b": "Curso de Microsoft Power BI desde cero | DAX, FUNCION CALCULATE (video 34)",
        "h": "20231005153656",
        "l": 793
    },
    {
        "i": 7,
        "j": "6exoydQQS5s",
        "b": "Curso de Microsoft Power BI desde cero | GENERAR INFORME DESDE CARGA DE DATOS WEB (video 8)",
        "h": "20230410174407",
        "l": 408
    },
    {
        "i": 42,
        "j": "77WaZVUEb9M",
        "b": "Curso de Microsoft Power BI desde cero | FILTROS (video 43)",
        "h": "20240307203430",
        "l": 1422
    },
    {
        "i": 71,
        "j": "9_n1T2t-qyw",
        "b": "Curso de Microsoft Power BI desde cero | VER INFORMES EN DISPOSITIVOS MOVILES (video 72)",
        "h": "20240411222817",
        "l": 1020
    },
    {
        "i": 14,
        "j": "Ak_dxaVrjOw",
        "b": "Curso de Microsoft Power BI desde cero | POWER QUERY,  DINAMIZACION DE COLUMNAS (video 15)",
        "h": "20230415220242",
        "l": 703
    },
    {
        "i": 70,
        "j": "AkEZSRRHoGg",
        "b": "Curso de Microsoft Power BI desde cero | PUBLICAR INFORMES EN INTERNET (video 71)",
        "h": "20240411155813",
        "l": 1211
    },
    {
        "i": 41,
        "j": "AU4f0LqCMhE",
        "b": "Curso de Microsoft Power BI desde cero | CREAR UNA JERARQUIA PERSONALIZADA (video 42)",
        "h": "20240307171218",
        "l": 434
    },
    {
        "i": 50,
        "j": "Ay8IXQIjH3w",
        "b": "Curso de Microsoft Power BI desde cero | TARJETAS  [AVANZADO](video 51)",
        "h": "20240320234507",
        "l": 1335
    },
    {
        "i": 72,
        "j": "b_If7N0WbQk",
        "b": "Curso de Microsoft Power BI desde cero | DAX AVANZADO (video 73)",
        "h": "20240412193332",
        "l": 1422
    },
    {
        "i": 27,
        "j": "BMFGfvIuhss",
        "b": "Curso de Microsoft Power BI desde cero | MAPAS [parte 2 ](video 28)",
        "h": "20230425212905",
        "l": 385
    },
    {
        "i": 1,
        "j": "C6kg1-a2BRQ",
        "b": "Curso de Microsoft Power BI desde cero | DESCARGA E INSTALACION (video 2)",
        "h": "20241127205354",
        "l": 308
    },
    {
        "i": 38,
        "j": "cnM2M16Y-70",
        "b": "Curso de Microsoft Power BI desde cero | RELACION DE TABLAS UNO A MUCHOS (video 39)",
        "h": "20240305161122",
        "l": 606
    },
    {
        "i": 61,
        "j": "CuVL_ql_AwQ",
        "b": "Curso de Microsoft Power BI desde cero | TRANSFORMACION DE DATOS DE TIEMPO -ACTUALIZACION (video 62)",
        "h": "20240329203319",
        "l": 674
    },
    {
        "i": 55,
        "j": "dDl-Rcl0zdA",
        "b": "Curso de Microsoft Power BI desde cero | NUBES DE PALABRAS  (video 56)",
        "h": "20240325225510",
        "l": 787
    },
    {
        "i": 23,
        "j": "dqDAkXWI9uo",
        "b": "Curso de Microsoft Power BI desde cero | GRAFICOS, PRACTICA FINAL (video 24)",
        "h": "20230421234834",
        "l": 684
    },
    {
        "i": 57,
        "j": "dyfOJHJMKbs",
        "b": "Curso de Microsoft Power BI desde cero | ESPECIFICAR DOCUMENTOS (video 58)",
        "h": "20240327213956",
        "l": 506
    },
    {
        "i": 29,
        "j": "E2toY-yKLcE",
        "b": "Curso de Microsoft Power BI desde cero | DAX,  CONTEO DE REGISTROS EN COLUMNAS (video 30)",
        "h": "20230427130053",
        "l": 321
    },
    {
        "i": 24,
        "j": "ftHaG41sdvI",
        "b": "Curso de Microsoft Power BI desde cero | GRAFICOS [EXTRA], CARGA DE IMAGENES WEB  (video 25)",
        "h": "20230422162441",
        "l": 546
    },
    {
        "i": 17,
        "j": "Gh8b5KiMc-8",
        "b": "Curso de Microsoft Power BI desde cero | MANEJO DE GRAFICOS, PARTE 2 (video 18)",
        "h": "20230417224614",
        "l": 836
    },
    {
        "i": 51,
        "j": "GIdBtoutKWQ",
        "b": "Curso de Microsoft Power BI desde cero | GRAFICOS DE CINTAS ](video 52)",
        "h": "20240323174813",
        "l": 702
    },
    {
        "i": 53,
        "j": "h4jEsdr39Kc",
        "b": "Curso de Microsoft Power BI desde cero | REPORTES CON INTELIGENCIA ARTIFICAL parte 2 (video 54)",
        "h": "20240324175854",
        "l": 598
    },
    {
        "i": 9,
        "j": "HlhOAzcnE3w",
        "b": "Curso de Microsoft Power BI desde cero | QUERY EDITOR, ELIMINAR COLUMNAS (video 10)",
        "h": "20230411153642",
        "l": 283
    },
    {
        "i": 20,
        "j": "IJ2lK5c09Ig",
        "b": "Curso de Microsoft Power BI desde cero | MANEJO DE GRAFICOS SERIE -TIEMPO (video 21)",
        "h": "20230420210829",
        "l": 656
    },
    {
        "i": 10,
        "j": "IQ8g6Q3xJu0",
        "b": "Curso de Microsoft Power BI desde cero | QUERY EDITOR, ELIMINAR FILAS, FILTRAR VALOR NULL(video 11)",
        "h": "20230411161545",
        "l": 509
    },
    {
        "i": 28,
        "j": "IRgZjnwvvQs",
        "b": "Curso de Microsoft Power BI desde cero | DAX,  INTRODUCCION (video 29)",
        "h": "20230426234143",
        "l": 739
    },
    {
        "i": 26,
        "j": "IxM_iw4cuqo",
        "b": "Curso de Microsoft Power BI desde cero | MAPAS [parte 1 ](video 27)",
        "h": "20230425001505",
        "l": 617
    },
    {
        "i": 60,
        "j": "j6CYw1cx4Ng",
        "b": "Curso de Microsoft Power BI desde cero | TRANSFORMACION DE DATOS NUMERICOS- ACTUALIZACION (video 61)",
        "h": "20240329185358",
        "l": 504
    },
    {
        "i": 47,
        "j": "k1EDJj3mfko",
        "b": "Curso de Microsoft Power BI desde cero | TEMAS Y DISEﾃ前S II (video 48)",
        "h": "20240318230545",
        "l": 751
    },
    {
        "i": 2,
        "j": "L74STt9hnu4",
        "b": "Curso de Microsoft Power BI desde cero | NAVEGACION INICIAL (video 3)",
        "h": "20230406222847",
        "l": 584
    },
    {
        "i": 18,
        "j": "ld3AEK8T_OM",
        "b": "Curso de Microsoft Power BI desde cero | MANEJO DE GRAFICOS, PARTE 3 (video 19)",
        "h": "20230418122614",
        "l": 491
    },
    {
        "i": 49,
        "j": "LDEpA_6-NTs",
        "b": "Curso de Microsoft Power BI desde cero | TABLAS Y MATRICES [AVANZADO](video 50)",
        "h": "20240319235015",
        "l": 968
    },
    {
        "i": 56,
        "j": "mZcgCzixeEI",
        "b": "Curso de Microsoft Power BI desde cero | PARAMETROS DE CONEXION (video 57)",
        "h": "20240327000130",
        "l": 1005
    },
    {
        "i": 69,
        "j": "N8gXJiz1wis",
        "b": "Curso de Microsoft Power BI desde cero | COLUMNAS CONDICIONALES (video 70)",
        "h": "20240408222401",
        "l": 1392
    },
    {
        "i": 43,
        "j": "NciTZ_8wcOU",
        "b": "Curso de Microsoft Power BI desde cero | PRACTICA FINAL, JERARQUIAS, Y FILTROS(video 44)",
        "h": "20240308145157",
        "l": 1328
    },
    {
        "i": 11,
        "j": "neLgEhWXXAI",
        "b": "Curso de Microsoft Power BI desde cero | QUERY EDITOR, FORMATEAR COLUMNAS, SEPARAR DATOS (video 12)",
        "h": "20230411221726",
        "l": 561
    },
    {
        "i": 13,
        "j": "NEy8z2XhyXU",
        "b": "Curso de Microsoft Power BI desde cero | POWER QUERY, EJERCICIO (video 14)",
        "h": "20230414001226",
        "l": 818
    },
    {
        "i": 46,
        "j": "oHoMlGRPcm8",
        "b": "Curso de Microsoft Power BI desde cero | TEMAS Y DISEﾃ前S (video 47)",
        "h": "20240318183413",
        "l": 784
    },
    {
        "i": 16,
        "j": "okkl2MjlzHk",
        "b": "Curso de Microsoft Power BI desde cero | MANEJO DE GRAFICOS, PARTE 1 (video 17)",
        "h": "20230417173702",
        "l": 896
    },
    {
        "i": 0,
        "j": "oQ4q2CSXP4M",
        "b": "Curso de Microsoft Power BI desde cero | INTRODUCCION (video 1)",
        "h": "20230405200317",
        "l": 827
    },
    {
        "i": 40,
        "j": "paPInPowldc",
        "b": "Curso de Microsoft Power BI desde cero | JERARQUIA DE FECHAS (video 41)",
        "h": "20240305231001",
        "l": 883
    },
    {
        "i": 19,
        "j": "pfBRLz-CVSM",
        "b": "Curso de Microsoft Power BI desde cero | MANEJO DE GRAFICOS, BARRAS DISTRIBUCION (video 20)",
        "h": "20230420162944",
        "l": 470
    },
    {
        "i": 34,
        "j": "pV2EF9WjP1U",
        "b": "Curso de Microsoft Power BI desde cero | DAX, AGRUPAMIENTO DE FUNCIONES (video 35)",
        "h": "20231006232052",
        "l": 355
    },
    {
        "i": 5,
        "j": "QcJ_J9WWM8w",
        "b": "Curso de Microsoft Power BI desde cero | IMPORTAR DATOS DESDE PAGINA WEB(video 6)",
        "h": "20230408221545",
        "l": 398
    },
    {
        "i": 4,
        "j": "QMofo-FrDq0",
        "b": "Curso de Microsoft Power BI desde cero | IMPORTAR DATOS DESDE ARCHIVO EXCEL(video 5)",
        "h": "20230408213955",
        "l": 298
    },
    {
        "i": 54,
        "j": "qZFIqzEuJgY",
        "b": "Curso de Microsoft Power BI desde cero | PLUGGINS, SANKEY (video 55)",
        "h": "20240324210116",
        "l": 892
    },
    {
        "i": 8,
        "j": "RPgLfNONS78",
        "b": "Curso de Microsoft Power BI desde cero | QUERY EDITOR [INTRODUCCION](video 9)",
        "h": "20230411135231",
        "l": 527
    },
    {
        "i": 66,
        "j": "rwFnB_S6ovM",
        "b": "Curso de Microsoft Power BI desde cero | DEPURACION DE TABLAS (video 67)",
        "h": "20240402234927",
        "l": 538
    },
    {
        "i": 65,
        "j": "rxGXtxeoVgA",
        "b": "Curso de Microsoft Power BI desde cero | AGRUPAMIENTO DE DATOS EN COLUMNAS (video 66)",
        "h": "20240402221753",
        "l": 533
    },
    {
        "i": 68,
        "j": "sQpO6Jn6NEw",
        "b": "Curso de Microsoft Power BI desde cero | CONSULTAS A PARTIR DE EJEMPLOS (video 69)",
        "h": "20240425220855",
        "l": 831
    },
    {
        "i": 21,
        "j": "uD0cn4TuAjM",
        "b": "Curso de Microsoft Power BI desde cero | MANEJO DE GRAFICOS DE TABLA (video 22)",
        "h": "20230420215410",
        "l": 511
    },
    {
        "i": 48,
        "j": "Uiug7nOWJLU",
        "b": "Curso de Microsoft Power BI desde cero | TEMAS Y DISEﾃ前S III (video 49)",
        "h": "20240319223607",
        "l": 403
    },
    {
        "i": 35,
        "j": "V5dCZNZO_cI",
        "b": "Curso de Microsoft Power BI desde cero | INTRODUCCION A PROYECTOS (video 36)",
        "h": "20240302183822",
        "l": 303
    },
    {
        "i": 58,
        "j": "v88KB7VQuMw",
        "b": "Curso de Microsoft Power BI desde cero | CARGA DE DATOS DE LA NUBE DE GOOGLE (video 59)",
        "h": "20240327233009",
        "l": 373
    },
    {
        "i": 22,
        "j": "vZUHaws1OVg",
        "b": "Curso de Microsoft Power BI desde cero | MANEJO DE GRAFICOS - MATRICES (video 23)",
        "h": "20230421222918",
        "l": 382
    },
    {
        "i": 63,
        "j": "w_Ie59RF6YI",
        "b": "Curso de Microsoft Power BI desde cero | COMBINAR TABLAS Y CONSULTAS (video 64)",
        "h": "20240401231041",
        "l": 1018
    },
    {
        "i": 45,
        "j": "WpoFFE-6W0A",
        "b": "Curso de Microsoft Power BI desde cero | LAYOUTS Y STORYTELLING [DISEﾃ前S (video 46)",
        "h": "20240315130352",
        "l": 786
    },
    {
        "i": 6,
        "j": "xr2mzjzBCsM",
        "b": "Curso de Microsoft Power BI desde cero | IMPORTAR DATOS DESDE UN ARCHIVO EN PDF (video 7)",
        "h": "20230408225527",
        "l": 199
    },
    {
        "i": 12,
        "j": "xUdmyBXixog",
        "b": "Curso de Microsoft Power BI desde cero | COLUMNAS CALCULADAS, REEMPLAZO DE VALORES (video 13)",
        "h": "20230413220948",
        "l": 690
    },
    {
        "i": 62,
        "j": "y7eu2YrIgzU",
        "b": "Curso de Microsoft Power BI desde cero | CONFIGURACION REGIONAL POWER QUERY (video 63)",
        "h": "20240330174131",
        "l": 690
    },
    {
        "i": 52,
        "j": "yDNaxQk4sMk",
        "b": "Curso de Microsoft Power BI desde cero | REPORTES CON INTELIGENCIA ARTIFICAL (video 53)",
        "h": "20240323215737",
        "l": 1090
    },
    {
        "i": 64,
        "j": "yFOYsZVXCis",
        "b": "Curso de Microsoft Power BI desde cero | ANEXAR TABLAS Y CONSULTAS (video 65)",
        "h": "20240402200707",
        "l": 529
    },
    {
        "i": 36,
        "j": "yoGQXpQf-bM",
        "b": "Curso de Microsoft Power BI desde cero | RELACION ENTRE TABLAS (video 37)",
        "h": "20240302213441",
        "l": 773
    },
    {
        "i": 30,
        "j": "ypqr1ub08nI",
        "b": "Curso de Microsoft Power BI desde cero | DAX,  DIVISION ENTRE COLUMNAS (video 31)",
        "h": "20231003233653",
        "l": 433
    },
    {
        "i": 15,
        "j": "Z_PgHi7bb_E",
        "b": "Curso de Microsoft Power BI desde cero | AGRUPAMIENTO DE DATOS, CONSOLIDAR CONSULTAS  (video 16)",
        "h": "20230415230801",
        "l": 761
    },
    {
        "i": 31,
        "j": "zrVWa6DqoPI",
        "b": "Curso de Microsoft Power BI desde cero | DAX, FUNCION AVERAGE  (video 32)",
        "h": "20231004120214",
        "l": 722
    }
]