[
    {
        "i": 1,
        "j": "2tvAPF7Kxs0",
        "b": "Diseño de Layouts - LinearLayout - Curso de Android en Kotlin",
        "h": "20200818133948"
    },
    {
        "i": 2,
        "j": "eO-Lg3Y6IzI",
        "b": "⚠️ ¿Todavía no usas ConstraintLayout? [TUTORIAL] - Aprende a CREAR LAYOUTS para ANDROID ► 2021",
        "h": "20201226155859"
    },
    {
        "i": 3,
        "j": "meX4tEOGpac",
        "b": "📑 Añadir FUENTES en ANDROID [FontFamily] - ❇️ Fuentes personalizadas en Android Studio 2021",
        "h": "20210328182842"
    },
    {
        "i": 0,
        "j": "xz7U_4Ob6Lg",
        "b": "Diseño de Layouts - FrameLayout - Curso de Android en Kotlin",
        "h": "20200803161315"
    }
]