[
    {
        "i": 35,
        "j": "_7T9wMWmsuA",
        "b": "🟢CURSO DE BELENISMO BÁSICO - SOBRE EL CURSO, COMENTARIOS E IMPRESIONES",
        "h": "20231207220802",
        "l": 388
    },
    {
        "i": 27,
        "j": "_Ne8bRVJR3o",
        "b": "🟡CURSO DE BELENISMO BÁSICO - Lección 27: fuente básica",
        "h": "20231028110159",
        "l": 1217
    },
    {
        "i": 34,
        "j": "-KE8EAJhtrc",
        "b": "🟢CURSO DE BELENISMO BÁSICO - Lección 34: El montaje, figuras y complementos",
        "h": "20231207213840",
        "l": 235
    },
    {
        "i": 17,
        "j": "0A2yvrZKt6E",
        "b": "🟢 CURSO DE BELENISMO BÁSICO - Lección 17: integrar peanas",
        "h": "20230817171126",
        "l": 536
    },
    {
        "i": 31,
        "j": "0JVIBuJuemY",
        "b": "🟢CURSO DE BELENISMO BÁSICO - Lección 31: El ensamblaje 3, las rocas y tierra",
        "h": "20231123202129",
        "l": 751
    },
    {
        "i": 24,
        "j": "65lzSHYOZ2c",
        "b": "🟢CURSO DE BELENISMO BÁSICO - Lección 24: Las antorchas",
        "h": "20231005170213",
        "l": 512
    },
    {
        "i": 1,
        "j": "8JbB4tlGOKY",
        "b": "🟢 CURSO DE BELENISMO BÁSICO - Lección 2: casa hebrea básica",
        "h": "20230421160505",
        "l": 882
    },
    {
        "i": 37,
        "j": "9HSKwiRP1kw",
        "b": "⚪ BELENES CURSO 2023 - SEGUNDA PARTE",
        "h": "20240104171002",
        "l": 288
    },
    {
        "i": 14,
        "j": "aQzVz0CZvuc",
        "b": "🟢 CURSO DE BELENISMO BÁSICO - Lección 14: tejadillos de caña",
        "h": "20230720163942",
        "l": 457
    },
    {
        "i": 2,
        "j": "B9G1NWfZoYI",
        "b": "🟢 CURSO DE BELENISMO BÁSICO - Lección 3: casa hebrea con puerta de piedra",
        "h": "20230429123807",
        "l": 645
    },
    {
        "i": 7,
        "j": "BRi0tLbwFLc",
        "b": "🟢 CURSO DE BELENISMO BÁSICO - Lección 8: envejecer madera",
        "h": "20230602134703",
        "l": 277
    },
    {
        "i": 32,
        "j": "dbj-KhBvuA0",
        "b": "🟢CURSO DE BELENISMO BÁSICO - Lección 32: El ensamblaje 4, casas unidas",
        "h": "20231130205233",
        "l": 388
    },
    {
        "i": 21,
        "j": "DTFEG-HLtQY",
        "b": "🟢 CURSO DE BELENISMO BÁSICO - Lección 21: Los toldos",
        "h": "20230915145225",
        "l": 340
    },
    {
        "i": 0,
        "j": "EsCAccxuhsM",
        "b": "🟢 CURSO DE BELENISMO BÁSICO - Lección 1: presentación y materiales",
        "h": "20230414141304",
        "l": 1102
    },
    {
        "i": 8,
        "j": "F3yIfp7BIhI",
        "b": "🟢 CURSO DE BELENISMO BÁSICO - Lección 9: casa con ladrillos y madera",
        "h": "20230608113544",
        "l": 1071
    },
    {
        "i": 25,
        "j": "Gyc0Wsika4M",
        "b": "🟢CURSO DE BELENISMO BÁSICO - Lección 25: Los pebeteros",
        "h": "20231013120058",
        "l": 396
    },
    {
        "i": 33,
        "j": "H8mY5B39tXw",
        "b": "🟢CURSO DE BELENISMO BÁSICO - Lección 33: La vegetación",
        "h": "20231130211429",
        "l": 685
    },
    {
        "i": 38,
        "j": "I6SBPbLCXkk",
        "b": "Private video",
        "h": "20230427153341",
        "l": 0
    },
    {
        "i": 11,
        "j": "ILAOG8V7Vk8",
        "b": "🟢 CURSO DE BELENISMO BÁSICO - Lección 12: hacer tejas",
        "h": "20230630043748",
        "l": 479
    },
    {
        "i": 29,
        "j": "lbbCMaRhNBQ",
        "b": "🟢CURSO DE BELENISMO BÁSICO - Lección 29: El ensamblaje 1, niveles principales",
        "h": "20231109172251",
        "l": 456
    },
    {
        "i": 10,
        "j": "lCtE-fHN-R0",
        "b": "🟢 CURSO DE BELENISMO BÁSICO - Lección 11: casa con descorchón",
        "h": "20230622161023",
        "l": 581
    },
    {
        "i": 3,
        "j": "mBMQmkBkLRE",
        "b": "🟢 CURSO DE BELENISMO BÁSICO - Lección 4: casa con zócalo de piedra",
        "h": "20230505160502",
        "l": 607
    },
    {
        "i": 18,
        "j": "mRXyZeoPn90",
        "b": "🟢 CURSO DE BELENISMO BÁSICO - Lección 18: puerta de madera",
        "h": "20230824045018",
        "l": 723
    },
    {
        "i": 28,
        "j": "NaPelLusGYk",
        "b": "🟡CURSO DE BELENISMO BÁSICO - Lección 28: EL PORTAL DE BELÉN",
        "h": "20231102093346",
        "l": 1907
    },
    {
        "i": 23,
        "j": "njdnGeeAPAA",
        "b": "🟢CURSO DE BELENISMO BÁSICO - Lección 23: Conceptos básicos de iluminación LED",
        "h": "20230929163423",
        "l": 596
    },
    {
        "i": 36,
        "j": "PyPz5-I6qIQ",
        "b": "⚪ BELENES CURSO 2023",
        "h": "20231229000300",
        "l": 864
    },
    {
        "i": 22,
        "j": "Qhre9elUfaI",
        "b": "🟢CURSO DE BELENISMO BÁSICO - Lección 22: Las persianas",
        "h": "20230922112107",
        "l": 223
    },
    {
        "i": 9,
        "j": "s9oKwCEew28",
        "b": "🟢 CURSO DE BELENISMO BÁSICO - Lección 10: sombras y negros",
        "h": "20230622161004",
        "l": 554
    },
    {
        "i": 5,
        "j": "tWqWhofNM38",
        "b": "🟢 CURSO DE BELENISMO BÁSICO - Lección 6: colores básicos",
        "h": "20230518171302",
        "l": 884
    },
    {
        "i": 6,
        "j": "u2Dd2RRyNpE",
        "b": "🟢 CURSO DE BELENISMO BÁSICO - Lección 7: hacer ladrillos",
        "h": "20230525155121",
        "l": 591
    },
    {
        "i": 16,
        "j": "VMaSGIU8UD8",
        "b": "🟢 CURSO DE BELENISMO BÁSICO - Lección 16: empedrado o adoquinado",
        "h": "20230804084850",
        "l": 482
    },
    {
        "i": 13,
        "j": "vqolrqizmig",
        "b": "🟢 CURSO DE BELENISMO BÁSICO - PLANIFICACIÓN RESTO DEL CURSO",
        "h": "20230712170804",
        "l": 705
    },
    {
        "i": 26,
        "j": "w-fTOl0UcXs",
        "b": "🟢CURSO DE BELENISMO BÁSICO - Lección 26: Iluminación básica belenes",
        "h": "20231019193822",
        "l": 697
    },
    {
        "i": 30,
        "j": "wl3NFUuM_Sg",
        "b": "🟢CURSO DE BELENISMO BÁSICO - Lección 30: El ensamblaje 2, la electricidad, conexiones básicas",
        "h": "20231227055058",
        "l": 541
    },
    {
        "i": 4,
        "j": "wrhqo2ayvrc",
        "b": "🟢 CURSO DE BELENISMO BÁSICO - Lección 5: la escayola",
        "h": "20230514100401",
        "l": 889
    },
    {
        "i": 19,
        "j": "wsjOYEjGTVM",
        "b": "🟢 CURSO DE BELENISMO BÁSICO - Lección 19: las celosías",
        "h": "20230901194603",
        "l": 510
    },
    {
        "i": 12,
        "j": "xlK__f7AvGk",
        "b": "🟢 CURSO DE BELENISMO BÁSICO - Lección 13: casa con tejado",
        "h": "20230705194600",
        "l": 1089
    },
    {
        "i": 20,
        "j": "YBNGj182AJY",
        "b": "🟢 CURSO DE BELENISMO BÁSICO - Lección 20: las cortinas",
        "h": "20230908114656",
        "l": 308
    },
    {
        "i": 15,
        "j": "YNeT7pyWH-A",
        "b": "🟢 CURSO DE BELENISMO BÁSICO - Lección 15: arco de piedra",
        "h": "20230727102012",
        "l": 592
    }
]