[
    {
        "i": 3,
        "j": "AjDA2wsfv-Q",
        "b": "Curso completo de informática basica (computación) DISP. DE ENTRADA Y SALIDA | USUARIOS [video 4]"
    },
    {
        "i": 9,
        "j": "CJ-2LjCee00",
        "b": "Curso completo de informática basica (computación) SISTEMAS OPERATIVOS parte 1 [video 10]"
    },
    {
        "i": 14,
        "j": "D70LFfb2jn4",
        "b": "Curso completo de informática basic,  SISTEMAS OPERATIVOS - EVOLUCION DE UBUNTU parte I  [video 15]"
    },
    {
        "i": 6,
        "j": "e8bk8Ze3-CI",
        "b": "Curso completo de informática basica (computación) MONITORES Y TARJETAS GRAFICAS  [video 7]"
    },
    {
        "i": 7,
        "j": "fcvre7V6BI0",
        "b": "Curso completo de informática basica (computación) MEMORIAS, RELOJ INTERNO Y BUS [video 8]"
    },
    {
        "i": 8,
        "j": "fQBwlFVsQIc",
        "b": "Curso completo de informática basica (computación) EL PROCESADOR [video 9]"
    },
    {
        "i": 2,
        "j": "Il74o5rUBb4",
        "b": "Curso completo de informática basica (computación) COMPONENTES DE UNA COMPUTADORA [video 3]"
    },
    {
        "i": 11,
        "j": "iMb1QvJwVNg",
        "b": "Curso completo de informática basica, SISTEMAS OPERATIVOS | EVOLUCION DE WINDOWS [video 12]"
    },
    {
        "i": 1,
        "j": "mTbC3NRz_7Q",
        "b": "Curso completo de informática basica (computación) LA COMPUTADORA [video 2]"
    },
    {
        "i": 5,
        "j": "mUAd_CO3g9A",
        "b": "Curso completo de informática basica (computación) SCANERS, GAMEPADS, CAMARAS [video 6]"
    },
    {
        "i": 15,
        "j": "nC4mrFiXXGk",
        "b": "Curso completo de informática basica, SISTEMAS OPERATIVOS | EVOLUCION DE UBUNTU parte II  [video 16]"
    },
    {
        "i": 0,
        "j": "o_78Ue_EUeI",
        "b": "Curso completo de informática basica (computación) INTRODUCCION [video 1]"
    },
    {
        "i": 10,
        "j": "sBRMaiDEqL4",
        "b": "Curso completo de informática basica (computación)  PROGRAMAS [video 11]"
    },
    {
        "i": 4,
        "j": "uQYjGhF-o_s",
        "b": "Curso completo de informática basica (computación) MOUSE Y TECLADO [video 5]"
    },
    {
        "i": 13,
        "j": "x9tBX5KLUcc",
        "b": "Curso completo de informática basica, SISTEMAS OPERATIVOS | EVOLUCION DE MAC OS parte II  [video 14]"
    },
    {
        "i": 12,
        "j": "xz54GDzrXKM",
        "b": "Curso completo de informática basica, SISTEMAS OPERATIVOS | EVOLUCION DE MAC OS parte I  [video 13]"
    }
]